__init__.py
geminiai_cli/__init__.py
geminiai_cli/args.py
geminiai_cli/b2.py
geminiai_cli/backup.py
geminiai_cli/banner.py
geminiai_cli/chat.py
geminiai_cli/check_b2.py
geminiai_cli/cli.py
geminiai_cli/cloud_factory.py
geminiai_cli/cloud_s3.py
geminiai_cli/cloud_storage.py
geminiai_cli/config.py
geminiai_cli/cooldown.py
geminiai_cli/credentials.py
geminiai_cli/doctor.py
geminiai_cli/history.py
geminiai_cli/integrity.py
geminiai_cli/list_backups.py
geminiai_cli/login.py
geminiai_cli/logout.py
geminiai_cli/profile.py
geminiai_cli/project_config.py
geminiai_cli/prune.py
geminiai_cli/recommend.py
geminiai_cli/reset_helpers.py
geminiai_cli/restore.py
geminiai_cli/session.py
geminiai_cli/settings.py
geminiai_cli/settings_cli.py
geminiai_cli/stats.py
geminiai_cli/sync.py
geminiai_cli/ui.py
geminiai_cli/update.py
geminiai_cli/utils.py
geminiai_cli/wizard.py
geminiai_cli-16.0.1.dist-info/METADATA
geminiai_cli-16.0.1.dist-info/WHEEL
geminiai_cli-16.0.1.dist-info/entry_points.txt
geminiai_cli-16.0.1.dist-info/top_level.txt
geminiai_cli-16.0.1.dist-info/RECORD
